twitter_utils/__init__.py
twitter_utils/rapid_api.py
twitter_utils/time.py
twitter_utils/twitter.py
twitter_utils/types.py
rapid_api_twitter_utils-0.0.8.1.dist-info/LICENSE
rapid_api_twitter_utils-0.0.8.1.dist-info/METADATA
rapid_api_twitter_utils-0.0.8.1.dist-info/WHEEL
rapid_api_twitter_utils-0.0.8.1.dist-info/top_level.txt
rapid_api_twitter_utils-0.0.8.1.dist-info/RECORD
