Metadata-Version: 2.1
Name: rapid-api-twitter-utils
Version: 0.0.8.1
Summary: Useful functions for use with Twitter API from RapidAPI
Author-email: Mohamed Hassan <mdhn6832@gmail.com>
License-File: LICENSE
